tonic_validate/__init__.py
tonic_validate/classes/__init__.py
tonic_validate/classes/benchmark.py
tonic_validate/classes/exceptions.py
tonic_validate/classes/llm_response.py
tonic_validate/classes/run.py
tonic_validate/classes/user_info.py
tonic_validate/config.py
tonic_validate/metrics/__init__.py
tonic_validate/metrics/answer_consistency_binary_metric.py
tonic_validate/metrics/answer_consistency_metric.py
tonic_validate/metrics/answer_contains_pii_metric.py
tonic_validate/metrics/answer_match_metric.py
tonic_validate/metrics/answer_similarity_metric.py
tonic_validate/metrics/augmentation_accuracy_metric.py
tonic_validate/metrics/augmentation_precision_metric.py
tonic_validate/metrics/binary_metric.py
tonic_validate/metrics/contains_text_metric.py
tonic_validate/metrics/context_contains_pii_metric.py
tonic_validate/metrics/context_length_metric.py
tonic_validate/metrics/duplication_metric.py
tonic_validate/metrics/hate_speech_content_metric.py
tonic_validate/metrics/latency_metric.py
tonic_validate/metrics/metric.py
tonic_validate/metrics/regex_metric.py
tonic_validate/metrics/response_length_metric.py
tonic_validate/metrics/retrieval_precision_metric.py
tonic_validate/services/litellm_service.py
tonic_validate/services/openai_service.py
tonic_validate/tests/test_scorer.py
tonic_validate/utils/__init__.py
tonic_validate/utils/http_client.py
tonic_validate/utils/llm_cache.py
tonic_validate/utils/llm_calls.py
tonic_validate/utils/metrics_util.py
tonic_validate/utils/telemetry.py
tonic_validate/validate_api.py
tonic_validate/validate_monitorer.py
tonic_validate/validate_scorer.py
tonic_validate-6.2.0.dist-info/LICENSE
tonic_validate-6.2.0.dist-info/METADATA
tonic_validate-6.2.0.dist-info/WHEEL
tonic_validate-6.2.0.dist-info/RECORD
