Metadata-Version: 2.1
Name: tonic-validate
Version: 6.2.0
Summary: RAG evaluation metrics.
Author: Joe Ferrara
Author-email: joeferrara@tonic.ai
Requires-Python: >=3.8.1,<4.0.0
Classifier: Programming Language :: Python :: 3
Classifier: Programming Language :: Python :: 3.9
Classifier: Programming Language :: Python :: 3.10
Classifier: Programming Language :: Python :: 3.11
Classifier: Programming Language :: Python :: 3.12
Classifier: Programming Language :: Python :: 3.13
Requires-Dist: aioboto3 (>=12.4.0,<13.0.0)
Requires-Dist: appdirs (>=1.4.4,<2.0.0)
Requires-Dist: google-generativeai (>=0.5.2,<0.6.0) ; python_version >= "3.9"
Requires-Dist: litellm (>=1.35.8,<2.0.0)
Requires-Dist: openai (>=1.0.0)
Requires-Dist: pydantic (>=2.6.4,<3.0.0)
Requires-Dist: python-dotenv (>=1.0.1,<2.0.0)
Requires-Dist: tiktoken (>=0.7.0,<0.8.0)
Requires-Dist: tqdm (>=4.66.2,<5.0.0)
Requires-Dist: typing-extensions (>=4.10.0,<5.0.0)
